hydra_plugins/hydra_orion_sweeper/__init__.py
hydra_plugins/hydra_orion_sweeper/config.py
hydra_plugins/hydra_orion_sweeper/implementation.py
hydra_plugins/hydra_orion_sweeper/orion_sweeper.py
hydra_orion_sweeper-1.6.4.dist-info/METADATA
hydra_orion_sweeper-1.6.4.dist-info/WHEEL
hydra_orion_sweeper-1.6.4.dist-info/top_level.txt
hydra_orion_sweeper-1.6.4.dist-info/RECORD
