Metadata-Version: 2.1
Name: hydra-orion-sweeper
Version: 1.6.4
Summary: Hydra Orion Sweeper plugin
Home-page: https://orion.readthedocs.io/
Author: Pierre Delaunay
Author-email: pierre.delaunay@mila.quebec
Classifier: License :: OSI Approved :: MIT License
Classifier: Programming Language :: Python :: 3.7
Classifier: Programming Language :: Python :: 3.8
Classifier: Programming Language :: Python :: 3.9
Classifier: Programming Language :: Python :: 3.10
Classifier: Programming Language :: Python :: 3.11
Classifier: Operating System :: OS Independent
Classifier: Development Status :: 4 - Beta
Requires-Dist: typing-extensions
Requires-Dist: hydra-core
Requires-Dist: orion >=0.2.2
Requires-Dist: omegaconf
